README.md
setup.py
digital/__init__.py
digital.egg-info/PKG-INFO
digital.egg-info/SOURCES.txt
digital.egg-info/dependency_links.txt
digital.egg-info/not-zip-safe
digital.egg-info/requires.txt
digital.egg-info/top_level.txt